mdmailbox/__init__.py
mdmailbox/_docs.py
mdmailbox/authinfo.py
mdmailbox/cli.py
mdmailbox/email.py
mdmailbox/imap.py
mdmailbox/importer.py
mdmailbox/smtp.py
mdmailbox/validate.py
mdmailbox-0.1.13.dist-info/METADATA
mdmailbox-0.1.13.dist-info/WHEEL
mdmailbox-0.1.13.dist-info/entry_points.txt
mdmailbox-0.1.13.dist-info/RECORD
