Metadata-Version: 2.4
Name: mdmailbox
Version: 0.1.13
Summary: Email as plain text files with YAML frontmatter
Requires-Python: >=3.13
Requires-Dist: click>=8.0
Requires-Dist: pyyaml>=6.0
